[
  {
    "book_1": {
      "author": "andbes",
      "date": "24.06.2020",
      "images": {
        "1": { "author": "andbes", "url": "24.06.2020 - 1.1.png" },
        "2": { "author": "arcticsocks", "url": "24.06.2020 - 1.2.png" },
        "3": { "author": "barcat", "url": "24.06.2020 - 1.3.png" },
        "4": { "author": "hullperse", "url": "24.06.2020 - 1.4.png" }
      }
    },
    "book_2": {
      "author": "barcat",
      "date": "24.06.2020",
      "images": {
        "1": { "author": "barcat", "url": "24.06.2020 - 2.1.png" },
        "2": { "author": "hullperse", "url": "24.06.2020 - 2.2.png" },
        "3": { "author": "arcticsocks", "url": "24.06.2020 - 2.3.png" },
        "4": { "author": "andbes", "url": "24.06.2020 - 2.4.png" }
      }
    },
    "book_3": {
      "author": "hullperse",
      "date": "24.06.2020",
      "images": {
        "1": { "author": "hullperse", "url": "24.06.2020 - 3.1.png" },
        "2": { "author": "arcticsocks", "url": "24.06.2020 - 3.2.png" },
        "3": { "author": "andbes", "url": "24.06.2020 - 3.3.png" },
        "4": { "author": "barcat", "url": "24.06.2020 - 3.4.png" }
      }
    },
    "book_4": {
      "author": "arcticsocks",
      "date": "24.06.2020",
      "images": {
        "1": { "author": "arcticsocks", "url": "24.06.2020 - 4.1.png" },
        "2": { "author": "andbes", "url": "24.06.2020 - 4.2.png" },
        "3": { "author": "hullperse", "url": "24.06.2020 - 4.3.png" },
        "4": { "author": "barcat", "url": "24.06.2020 - 4.4.png" }
      }
    },
    "book_5": {
      "author": "andbes",
      "date": "05.07.2020",
      "images": {
        "1": { "author": "andbes", "url": "05.07.2020 - 1.1.png" },
        "2": { "author": "hullperse", "url": "05.07.2020 - 1.2.png" },
        "3": { "author": "barcat", "url": "05.07.2020 - 1.3.png" },
        "4": { "author": "arcticsocks", "url": "05.07.2020 - 1.4.png" }
      }
    },
    "book_6": {
      "author": "barcat",
      "date": "05.07.2020",
      "images": {
        "1": { "author": "barcat", "url": "05.07.2020 - 2.1.png" },
        "2": { "author": "arcticsocks", "url": "05.07.2020 - 2.2.png" },
        "3": { "author": "andbes", "url": "05.07.2020 - 2.3.png" },
        "4": { "author": "hullperse", "url": "05.07.2020 - 2.4.png" }
      }
    },
    "book_7": {
      "author": "hullperse",
      "date": "05.07.2020",
      "images": {
        "1": { "author": "hullperse", "url": "05.07.2020 - 3.1.png" },
        "2": { "author": "barcat", "url": "05.07.2020 - 3.2.png" },
        "3": { "author": "arcticsocks", "url": "05.07.2020 - 3.3.png" },
        "4": { "author": "andbes", "url": "05.07.2020 - 3.4.png" }
      }
    },
    "book_8": {
      "author": "arcticsocks",
      "date": "05.07.2020",
      "images": {
        "1": { "author": "arcticsocks", "url": "05.07.2020 - 4.1.png" },
        "2": { "author": "andbes", "url": "05.07.2020 - 4.2.png" },
        "3": { "author": "barcat", "url": "05.07.2020 - 4.3.png" },
        "4": { "author": "hullperse", "url": "05.07.2020 - 4.3.png" }
      }
    },
    "book_9": {
      "author": "andbes",
      "date": "09.10.2020",
      "images": {
        "1": { "author": "andbes", "url": "09.10.2020 - 1.1.png" },
        "2": { "author": "arcticsocks", "url": "09.10.2020 - 1.2.png" },
        "3": { "author": "hullperse", "url": "09.10.2020 - 1.3.png" },
        "4": { "author": "barcat", "url": "09.10.2020 - 1.4.png" }
      }
    },
    "book_10": {
      "author": "barcat",
      "date": "09.10.2020",
      "images": {
        "1": { "author": "barcat", "url": "09.10.2020 - 2.1.png" },
        "2": { "author": "hullperse", "url": "09.10.2020 - 2.2.png" },
        "3": { "author": "arcticsocks", "url": "09.10.2020 - 2.3.png" },
        "4": { "author": "andbes", "url": "09.10.2020 - 2.4.png" }
      }
    },
    "book_11": {
      "author": "arcticsocks",
      "date": "09.10.2020",
      "images": {
        "1": { "author": "arcticsocks", "url": "09.10.2020 - 3.1.png" },
        "2": { "author": "andbes", "url": "09.10.2020 - 3.2.png" },
        "3": { "author": "barcat", "url": "09.10.2020 - 3.3.png" },
        "4": { "author": "hullperse", "url": "09.10.2020 - 3.4.png" }
      }
    },
    "book_12": {
      "author": "hullperse",
      "date": "09.10.2020",
      "images": {
        "1": { "author": "hullperse", "url": "09.10.2020 - 4.1.png" },
        "2": { "author": "barcat", "url": "09.10.2020 - 4.2.png" },
        "3": { "author": "andbes", "url": "09.10.2020 - 4.3.png" },
        "4": { "author": "arcticsocks", "url": "09.10.2020 - 4.4.png" }
      }
    },
    "book_13": {
      "author": "barcat",
      "date": "10.10.2020",
      "images": {
        "1": { "author": "barcat", "url": "10.10.2020 - 1.1.png" },
        "2": { "author": "andbes", "url": "10.10.2020 - 1.2.png" },
        "3": { "author": "blinodel", "url": "10.10.2020 - 1.3.png" },
        "4": { "author": "arcticsocks", "url": "10.10.2020 - 1.4.png" },
        "5": { "author": "hullperse", "url": "10.10.2020 - 1.5.png" }
      }
    },
    "book_14": {
      "author": "andbes",
      "date": "10.10.2020",
      "images": {
        "1": { "author": "andbes", "url": "10.10.2020 - 2.1.png" },
        "2": { "author": "arcticsocks", "url": "10.10.2020 - 2.2.png" },
        "3": { "author": "hullperse", "url": "10.10.2020 - 2.3.png" },
        "4": { "author": "blinodel", "url": "10.10.2020 - 2.4.png" },
        "5": { "author": "barcat", "url": "10.10.2020 - 2.5.png" }
      }
    },
    "book_15": {
      "author": "blinodel",
      "date": "10.10.2020",
      "images": {
        "1": { "author": "blinodel", "url": "10.10.2020 - 3.1.png" },
        "2": { "author": "arcticsocks", "url": "10.10.2020 - 3.2.png" },
        "3": { "author": "barcat", "url": "10.10.2020 - 3.3.png" },
        "4": { "author": "hullperse", "url": "10.10.2020 - 3.4.png" },
        "5": { "author": "andbes", "url": "10.10.2020 - 3.5.png" }
      }
    },
    "book_16": {
      "author": "arcticsocks",
      "date": "10.10.2020",
      "images": {
        "1": { "author": "arcticsocks", "url": "10.10.2020 - 4.1.png" },
        "2": { "author": "barcat", "url": "10.10.2020 - 4.2.png" },
        "3": { "author": "hullperse", "url": "10.10.2020 - 4.3.png" },
        "4": { "author": "andbes", "url": "10.10.2020 - 4.4.png" },
        "5": { "author": "blinodel", "url": "10.10.2020 - 4.5.png" }
      }
    },
    "book_17": {
      "author": "hullperse",
      "date": "10.10.2020",
      "images": {
        "1": { "author": "hullperse", "url": "10.10.2020 - 5.1.png" },
        "2": { "author": "blinodel", "url": "10.10.2020 - 5.2.png" },
        "3": { "author": "arcticsocks", "url": "10.10.2020 - 5.3.png" },
        "4": { "author": "andbes", "url": "10.10.2020 - 5.4.png" },
        "5": { "author": "barcat", "url": "10.10.2020 - 5.5.png" }
      }
    },
    "book_18": {
      "author": "andbes",
      "date": "25.06.2020",
      "images": {
        "1": { "author": "andbes", "url": "25.06.2020 - 1.1.png" },
        "2": { "author": "barcat", "url": "25.06.2020 - 1.2.png" },
        "3": { "author": "arcticsocks", "url": "25.06.2020 - 1.3.png" },
        "4": { "author": "hullperse", "url": "25.06.2020 - 1.4.png" }
      }
    },
    "book_19": {
      "author": "barcat",
      "date": "25.06.2020",
      "images": {
        "1": { "author": "barcat", "url": "25.06.2020 - 2.1.png" },
        "2": { "author": "arcticsocks", "url": "25.06.2020 - 2.2.png" },
        "3": { "author": "andbes", "url": "25.06.2020 - 2.3.png" },
        "4": { "author": "hullperse", "url": "25.06.2020 - 2.4.png" }
      }
    },
    "book_20": {
      "author": "arcticsocks",
      "date": "25.06.2020",
      "images": {
        "1": { "author": "arcticsocks", "url": "25.06.2020 - 3.1.png" },
        "2": { "author": "andbes", "url": "25.06.2020 - 3.2.png" },
        "3": { "author": "barcat", "url": "25.06.2020 - 3.3.png" },
        "4": { "author": "hullperse", "url": "25.06.2020 - 3.4.png" }
      }
    },
    "book_21": {
      "author": "barcat",
      "date": "24.01.2021",
      "images": {
        "1": { "author": "barcat", "url": "24.01.2021 - 1.1.png" },
        "2": { "author": "sam b", "url": "24.01.2021 - 1.2.png" },
        "3": { "author": "arcticsocks", "url": "24.01.2021 - 1.3.png" },
        "4": { "author": "hullperse", "url": "24.01.2021 - 1.4.png" },
        "5": { "author": "andbes", "url": "24.01.2021 - 1.5.png" },
        "6": { "author": "reimilia", "url": "24.01.2021 - 1.6.png" }
      }
    },
    "book_22": {
      "author": "arcticsocks",
      "date": "24.01.2021",
      "images": {
        "1": { "author": "arcticsocks", "url": "24.01.2021 - 2.1.png" },
        "2": { "author": "reimilia", "url": "24.01.2021 - 2.2.png" },
        "3": { "author": "barcat", "url": "24.01.2021 - 2.3.png" },
        "4": { "author": "sam b", "url": "24.01.2021 - 2.4.png" },
        "5": { "author": "andbes", "url": "24.01.2021 - 2.5.png" },
        "6": { "author": "hullperse", "url": "24.01.2021 - 2.6.png" }
      }
    },
    "book_23": {
      "author": "andbes",
      "date": "24.01.2021",
      "images": {
        "1": { "author": "andbes", "url": "24.01.2021 - 3.1.png" },
        "2": { "author": "sam b", "url": "24.01.2021 - 3.2.png" },
        "3": { "author": "hullperse", "url": "24.01.2021 - 3.3.png" },
        "4": { "author": "reimilia", "url": "24.01.2021 - 3.4.png" },
        "5": { "author": "barcat", "url": "24.01.2021 - 3.5.png" },
        "6": { "author": "arcticsocks", "url": "24.01.2021 - 3.6.png" }
      }
    },
    "book_24": {
      "author": "sam b",
      "date": "24.01.2021",
      "images": {
        "1": { "author": "sam b", "url": "24.01.2021 - 4.1.png" },
        "2": { "author": "barcat", "url": "24.01.2021 - 4.2.png" },
        "3": { "author": "reimilia", "url": "24.01.2021 - 4.3.png" },
        "4": { "author": "andbes", "url": "24.01.2021 - 4.4.png" },
        "5": { "author": "arcticsocks", "url": "24.01.2021 - 4.5.png" },
        "6": { "author": "hullperse", "url": "24.01.2021 - 4.6.png" }
      }
    },
    "book_25": {
      "author": "hullperse",
      "date": "24.01.2021",
      "images": {
        "1": { "author": "hullperse", "url": "24.01.2021 - 5.1.png" },
        "2": { "author": "andbes", "url": "24.01.2021 - 5.2.png" },
        "3": { "author": "reimilia", "url": "24.01.2021 - 5.3.png" },
        "4": { "author": "barcat", "url": "24.01.2021 - 5.4.png" },
        "5": { "author": "arcticsocks", "url": "24.01.2021 - 5.5.png" },
        "6": { "author": "sam b", "url": "24.01.2021 - 5.6.png" }
      }
    },
    "book_26": {
      "author": "reimilia",
      "date": "24.01.2021",
      "images": {
        "1": { "author": "reimilia", "url": "24.01.2021 - 6.1.png" },
        "2": { "author": "hullperse", "url": "24.01.2021 - 6.2.png" },
        "3": { "author": "arcticsocks", "url": "24.01.2021 - 6.3.png" },
        "4": { "author": "andbes", "url": "24.01.2021 - 6.4.png" },
        "5": { "author": "sam b", "url": "24.01.2021 - 6.5.png" },
        "6": { "author": "barcat", "url": "24.01.2021 - 6.6.png" }
      }
    },
    "book_27": {
      "author": "andbes",
      "date": "13.02.2021",
      "images": {
        "1": { "author": "andbes", "url": "13.02.2021 - 1.1.png" },
        "2": { "author": "arcticsocks", "url": "13.02.2021 - 1.2.png" },
        "3": { "author": "reimilia", "url": "13.02.2021 - 1.3.png" },
        "4": { "author": "barcat", "url": "13.02.2021 - 1.4.png" },
        "5": { "author": "hullperse", "url": "13.02.2021 - 1.5.png" }
      }
    },
    "book_28": {
      "author": "arcticsocks",
      "date": "13.02.2021",
      "images": {
        "1": { "author": "arcticsocks", "url": "13.02.2021 - 2.1.png" },
        "2": { "author": "andbes", "url": "13.02.2021 - 2.2.png" },
        "3": { "author": "hullperse", "url": "13.02.2021 - 2.3.png" },
        "4": { "author": "barcat", "url": "13.02.2021 - 2.4.png" },
        "5": { "author": "reimilia", "url": "13.02.2021 - 2.5.png" }
      }
    },
    "book_29": {
      "author": "reimilia",
      "date": "13.02.2021",
      "images": {
        "1": { "author": "reimilia", "url": "13.02.2021 - 3.1.png" },
        "2": { "author": "hullperse", "url": "13.02.2021 - 3.2.png" },
        "3": { "author": "arcticsocks", "url": "13.02.2021 - 3.3.png" },
        "4": { "author": "barcat", "url": "13.02.2021 - 3.4.png" },
        "5": { "author": "andbes", "url": "13.02.2021 - 3.5.png" }
      }
    },
    "book_30": {
      "author": "hullperse",
      "date": "13.02.2021",
      "images": {
        "1": { "author": "hullperse", "url": "13.02.2021 - 4.1.png" },
        "2": { "author": "reimilia", "url": "13.02.2021 - 4.2.png" },
        "3": { "author": "barcat", "url": "13.02.2021 - 4.3.png" },
        "4": { "author": "arcticsocks", "url": "13.02.2021 - 4.4.png" },
        "5": { "author": "andbes", "url": "13.02.2021 - 4.5.png" }
      }
    },
    "book_31": {
      "author": "barcat",
      "date": "13.02.2021",
      "images": {
        "1": { "author": "barcat", "url": "13.02.2021 - 5.1.png" },
        "2": { "author": "arcticsocks", "url": "13.02.2021 - 5.2.png" },
        "3": { "author": "reimilia", "url": "13.02.2021 - 5.3.png" },
        "4": { "author": "andbes", "url": "13.02.2021 - 5.4.png" },
        "5": { "author": "hullperse", "url": "13.02.2021 - 5.5.png" }
      }
    },
    "book_32": {
      "author": "reimilia",
      "date": "17.02.2021",
      "images": {
        "1": { "author": "reimilia", "url": "17.02.2021 - 1.1.png" },
        "2": { "author": "andbes", "url": "17.02.2021 - 1.2.png" },
        "3": { "author": "hullperse", "url": "17.02.2021 - 1.3.png" },
        "4": { "author": "arcticsocks", "url": "17.02.2021 - 1.4.png" },
        "5": { "author": "barcat", "url": "17.02.2021 - 1.5.png" }
      }
    },
    "book_33": {
      "author": "arcticsocks",
      "date": "17.02.2021",
      "images": {
        "1": { "author": "arcticsocks", "url": "17.02.2021 - 2.1.png" },
        "2": { "author": "hullperse", "url": "17.02.2021 - 2.2.png" },
        "3": { "author": "reimilia", "url": "17.02.2021 - 2.3.png" },
        "4": { "author": "andbes", "url": "17.02.2021 - 2.4.png" },
        "5": { "author": "barcat", "url": "17.02.2021 - 2.5.png" }
      }
    },
    "book_34": {
      "author": "hullperse",
      "date": "17.02.2021",
      "images": {
        "1": { "author": "hullperse", "url": "17.02.2021 - 3.1.png" },
        "2": { "author": "barcat", "url": "17.02.2021 - 3.2.png" },
        "3": { "author": "reimilia", "url": "17.02.2021 - 3.3.png" },
        "4": { "author": "arcticsocks", "url": "17.02.2021 - 3.4.png" },
        "5": { "author": "andbes", "url": "17.02.2021 - 3.5.png" }
      }
    },
    "book_35": {
      "author": "andbes",
      "date": "17.02.2021",
      "images": {
        "1": { "author": "andbes", "url": "17.02.2021 - 4.1.png" },
        "2": { "author": "reimilia", "url": "17.02.2021 - 4.2.png" },
        "3": { "author": "arcticsocks", "url": "17.02.2021 - 4.3.png" },
        "4": { "author": "barcat", "url": "17.02.2021 - 4.4.png" },
        "5": { "author": "hullperse", "url": "17.02.2021 - 4.5.png" }
      }
    },
    "book_36": {
      "author": "barcat",
      "date": "17.02.2021",
      "images": {
        "1": { "author": "barcat", "url": "17.02.2021 - 5.1.png" },
        "2": { "author": "arcticsocks", "url": "17.02.2021 - 5.2.png" },
        "3": { "author": "hullperse", "url": "17.02.2021 - 5.3.png" },
        "4": { "author": "andbes", "url": "17.02.2021 - 5.4.png" },
        "5": { "author": "reimilia", "url": "17.02.2021 - 5.5.png" }
      }
    },
    "book_37": {
      "author": "reimilia",
      "date": "20.02.2021",
      "images": {
        "1": { "author": "reimilia", "url": "20.02.2021 - 1.1.png" },
        "2": { "author": "arcticsocks", "url": "20.02.2021 - 1.2.png" },
        "3": { "author": "hullperse", "url": "20.02.2021 - 1.3.png" },
        "4": { "author": "andbes", "url": "20.02.2021 - 1.4.png" },
        "5": { "author": "barcat", "url": "20.02.2021 - 1.5.png" }
      }
    },
    "book_38": {
      "author": "barcat",
      "date": "20.02.2021",
      "images": {
        "1": { "author": "barcat", "url": "20.02.2021 - 2.1.png" },
        "2": { "author": "hullperse", "url": "20.02.2021 - 2.2.png" },
        "3": { "author": "andbes", "url": "20.02.2021 - 2.3.png" },
        "4": { "author": "arcticsocks", "url": "20.02.2021 - 2.4.png" },
        "5": { "author": "reimilia", "url": "20.02.2021 - 2.5.png" }
      }
    },
    "book_39": {
      "author": "arcticsocks",
      "date": "20.02.2021",
      "images": {
        "1": { "author": "arcticsocks", "url": "20.02.2021 - 3.1.png" },
        "2": { "author": "barcat", "url": "20.02.2021 - 3.2.png" },
        "3": { "author": "reimilia", "url": "20.02.2021 - 3.3.png" },
        "4": { "author": "andbes", "url": "20.02.2021 - 3.4.png" },
        "5": { "author": "hullperse", "url": "20.02.2021 - 3.5.png" }
      }
    },
    "book_40": {
      "author": "andbes",
      "date": "20.02.2021",
      "images": {
        "1": { "author": "andbes", "url": "20.02.2021 - 4.1.png" },
        "2": { "author": "hullperse", "url": "20.02.2021 - 4.2.png" },
        "3": { "author": "reimilia", "url": "20.02.2021 - 4.3.png" },
        "4": { "author": "barcat", "url": "20.02.2021 - 4.4.png" },
        "5": { "author": "arcticsocks", "url": "20.02.2021 - 4.5.png" }
      }
    },
    "book_41": {
      "author": "hullperse",
      "date": "20.02.2021",
      "images": {
        "1": { "author": "hullperse", "url": "20.02.2021 - 5.1.png" },
        "2": { "author": "arcticsocks", "url": "20.02.2021 - 5.2.png" },
        "3": { "author": "barcat", "url": "20.02.2021 - 5.3.png" },
        "4": { "author": "reimilia", "url": "20.02.2021 - 5.4.png" },
        "5": { "author": "andbes", "url": "20.02.2021 - 5.5.png" }
      }
    },
    "book_42": {
      "author": "hullperse",
      "date": "24.02.2021",
      "images": {
        "1": { "author": "hullperse", "url": "24.02.2021 - 1.1.png" },
        "2": { "author": "barcat", "url": "24.02.2021 - 1.2.png" },
        "3": { "author": "arcticsocks", "url": "24.02.2021 - 1.3.png" },
        "4": { "author": "andbes", "url": "24.02.2021 - 1.4.png" },
        "5": { "author": "xenon", "url": "24.02.2021 - 1.5.png" },
        "6": { "author": "reimilia", "url": "24.02.2021 - 1.6.png" }
      }
    },
    "book_43": {
      "author": "reimilia",
      "date": "24.02.2021",
      "images": {
        "1": { "author": "reimilia", "url": "24.02.2021 - 2.1.png" },
        "2": { "author": "hullperse", "url": "24.02.2021 - 2.2.png" },
        "3": { "author": "arcticsocks", "url": "24.02.2021 - 2.3.png" },
        "4": { "author": "xenon", "url": "24.02.2021 - 2.4.png" },
        "5": { "author": "andbes", "url": "24.02.2021 - 2.5.png" },
        "6": { "author": "barcat", "url": "24.02.2021 - 2.6.png" }
      }
    },
    "book_44": {
      "author": "barcat",
      "date": "24.02.2021",
      "images": {
        "1": { "author": "barcat", "url": "24.02.2021 - 3.1.png" },
        "2": { "author": "xenon", "url": "24.02.2021 - 3.2.png" },
        "3": { "author": "andbes", "url": "24.02.2021 - 3.3.png" },
        "4": { "author": "hullperse", "url": "24.02.2021 - 3.4.png" },
        "5": { "author": "arcticsocks", "url": "24.02.2021 - 3.5.png" },
        "6": { "author": "reimilia", "url": "24.02.2021 - 3.6.png" }
      }
    },
    "book_45": {
      "author": "arcticsocks",
      "date": "24.02.2021",
      "images": {
        "1": { "author": "arcticsocks", "url": "24.02.2021 - 4.1.png" },
        "2": { "author": "xenon", "url": "24.02.2021 - 4.2.png" },
        "3": { "author": "barcat", "url": "24.02.2021 - 4.3.png" },
        "4": { "author": "reimilia", "url": "24.02.2021 - 4.4.png" },
        "5": { "author": "hullperse", "url": "24.02.2021 - 4.5.png" },
        "6": { "author": "andbes", "url": "24.02.2021 - 4.6.png" }
      }
    },
    "book_46": {
      "author": "xenon",
      "date": "24.02.2021",
      "images": {
        "1": { "author": "xenon", "url": "24.02.2021 - 5.1.png" },
        "2": { "author": "andbes", "url": "24.02.2021 - 5.2.png" },
        "3": { "author": "hullperse", "url": "24.02.2021 - 5.3.png" },
        "4": { "author": "reimilia", "url": "24.02.2021 - 5.4.png" },
        "5": { "author": "barcat", "url": "24.02.2021 - 5.5.png" },
        "6": { "author": "arcticsocks", "url": "24.02.2021 - 5.6.png" }
      }
    },
    "book_47": {
      "author": "andbes",
      "date": "24.02.2021",
      "images": {
        "1": { "author": "andbes", "url": "24.02.2021 - 6.1.png" },
        "2": { "author": "xenon", "url": "24.02.2021 - 6.2.png" },
        "3": { "author": "hullperse", "url": "24.02.2021 - 6.3.png" },
        "4": { "author": "arcticsocks", "url": "24.02.2021 - 6.4.png" },
        "5": { "author": "reimilia", "url": "24.02.2021 - 6.5.png" },
        "6": { "author": "barcat", "url": "24.02.2021 - 6.6.png" }
      }
    },
    "book_48": {
      "author": "arcticsocks",
      "date": "14.02.2021",
      "images": {
        "1": { "author": "arcticsocks", "url": "14.02.2021 - 1.1.png" },
        "2": { "author": "barcat", "url": "14.02.2021 - 1.2.png" },
        "3": { "author": "hullperse", "url": "14.02.2021 - 1.3.png" },
        "4": { "author": "andbes", "url": "14.02.2021 - 1.4.png" }
      }
    },
    "book_49": {
      "author": "andbes",
      "date": "14.02.2021",
      "images": {
        "1": { "author": "andbes", "url": "14.02.2021 - 2.1.png" },
        "2": { "author": "hullperse", "url": "14.02.2021 - 2.2.png" },
        "3": { "author": "barcat", "url": "14.02.2021 - 2.3.png" },
        "4": { "author": "arcticsocks", "url": "14.02.2021 - 2.4.png" }
      }
    },
    "book_50": {
      "author": "hullperse",
      "date": "14.02.2021",
      "images": {
        "1": { "author": "hullperse", "url": "14.02.2021 - 3.1.png" },
        "2": { "author": "arcticsocks", "url": "14.02.2021 - 3.2.png" },
        "3": { "author": "barcat", "url": "14.02.2021 - 3.3.png" },
        "4": { "author": "andbes", "url": "14.02.2021 - 3.4.png" }
      }
    },
    "book_51": {
      "author": "barcat",
      "date": "14.02.2021",
      "images": {
        "1": { "author": "barcat", "url": "14.02.2021 - 4.1.png" },
        "2": { "author": "andbes", "url": "14.02.2021 - 4.2.png" },
        "3": { "author": "arcticsocks", "url": "14.02.2021 - 4.3.png" },
        "4": { "author": "hullperse", "url": "14.02.2021 - 4.4.png" }
      }
    },
    "book_52": {
      "author": "andbes",
      "date": "28.02.2021",
      "images": {
        "1": { "author": "andbes", "url": "28.02.2021 - 1.1.png" },
        "2": { "author": "arcticsocks", "url": "28.02.2021 - 1.2.png" },
        "3": { "author": "hullperse", "url": "28.02.2021 - 1.3.png" },
        "4": { "author": "xenon", "url": "28.02.2021 - 1.4.png" },
        "5": { "author": "barcat", "url": "28.02.2021 - 1.5.png" },
        "6": { "author": "reimilia", "url": "28.02.2021 - 1.6.png" }
      }
    },
    "book_53": {
      "author": "barcat",
      "date": "28.02.2021",
      "images": {
        "1": { "author": "barcat", "url": "28.02.2021 - 2.1.png" },
        "2": { "author": "xenon", "url": "28.02.2021 - 2.2.png" },
        "3": { "author": "reimilia", "url": "28.02.2021 - 2.3.png" },
        "4": { "author": "arcticsocks", "url": "28.02.2021 - 2.4.png" },
        "5": { "author": "andbes", "url": "28.02.2021 - 2.5.png" },
        "6": { "author": "hullperse", "url": "28.02.2021 - 2.6.png" }
      }
    },
    "book_54": {
      "author": "hullperse",
      "date": "28.02.2021",
      "images": {
        "1": { "author": "hullperse", "url": "28.02.2021 - 3.1.png" },
        "2": { "author": "andbes", "url": "28.02.2021 - 3.2.png" },
        "3": { "author": "arcticsocks", "url": "28.02.2021 - 3.3.png" },
        "4": { "author": "barcat", "url": "28.02.2021 - 3.4.png" },
        "5": { "author": "xenon", "url": "28.02.2021 - 3.5.png" },
        "6": { "author": "reimilia", "url": "28.02.2021 - 3.6.png" }
      }
    },
    "book_55": {
      "author": "arcticsocks",
      "date": "28.02.2021",
      "images": {
        "1": { "author": "arcticsocks", "url": "28.02.2021 - 4.1.png" },
        "2": { "author": "xenon", "url": "28.02.2021 - 4.2.png" },
        "3": { "author": "hullperse", "url": "28.02.2021 - 4.3.png" },
        "4": { "author": "reimilia", "url": "28.02.2021 - 4.4.png" },
        "5": { "author": "barcat", "url": "28.02.2021 - 4.5.png" },
        "6": { "author": "andbes", "url": "28.02.2021 - 4.6.png" }
      }
    },
    "book_56": {
      "author": "reimilia",
      "date": "28.02.2021",
      "images": {
        "1": { "author": "reimilia", "url": "28.02.2021 - 5.1.png" },
        "2": { "author": "barcat", "url": "28.02.2021 - 5.2.png" },
        "3": { "author": "xenon", "url": "28.02.2021 - 5.3.png" },
        "4": { "author": "arcticsocks", "url": "28.02.2021 - 5.4.png" },
        "5": { "author": "hullperse", "url": "28.02.2021 - 5.5.png" },
        "6": { "author": "andbes", "url": "28.02.2021 - 5.6.png" }
      }
    },
    "book_57": {
      "author": "xenon",
      "date": "28.02.2021",
      "images": {
        "1": { "author": "xenon", "url": "28.02.2021 - 6.1.png" },
        "2": { "author": "andbes", "url": "28.02.2021 - 6.2.png" },
        "3": { "author": "barcat", "url": "28.02.2021 - 6.3.png" },
        "4": { "author": "reimilia", "url": "28.02.2021 - 6.4.png" },
        "5": { "author": "hullperse", "url": "28.02.2021 - 6.5.png" },
        "6": { "author": "arcticsocks", "url": "28.02.2021 - 6.6.png" }
      }
    },
    "book_58": {
      "author": "andbes",
      "date": "09.03.2021",
      "images": {
        "1": { "author": "andbes", "url": "09.03.2021 - 1.1.png" },
        "2": { "author": "xenon", "url": "09.03.2021 - 1.2.png" },
        "3": { "author": "hullperse", "url": "09.03.2021 - 1.3.png" },
        "4": { "author": "reimilia", "url": "09.03.2021 - 1.4.png" },
        "5": { "author": "arcticsocks", "url": "09.03.2021 - 1.5.png" }
      }
    },
    "book_59": {
      "author": "xenon",
      "date": "09.03.2021",
      "images": {
        "1": { "author": "xenon", "url": "09.03.2021 - 2.1.png" },
        "2": { "author": "andbes", "url": "09.03.2021 - 2.2.png" },
        "3": { "author": "arcticsocks", "url": "09.03.2021 - 2.3.png" },
        "4": { "author": "hullperse", "url": "09.03.2021 - 2.4.png" },
        "5": { "author": "reimilia", "url": "09.03.2021 - 2.5.png" }
      }
    },
    "book_60": {
      "author": "arcticsocks",
      "date": "09.03.2021",
      "images": {
        "1": { "author": "arcticsocks", "url": "09.03.2021 - 3.1.png" },
        "2": { "author": "reimilia", "url": "09.03.2021 - 3.2.png" },
        "3": { "author": "xenon", "url": "09.03.2021 - 3.3.png" },
        "4": { "author": "hullperse", "url": "09.03.2021 - 3.4.png" },
        "5": { "author": "andbes", "url": "09.03.2021 - 3.5.png" }
      }
    },
    "book_61": {
      "author": "reimilia",
      "date": "09.03.2021",
      "images": {
        "1": { "author": "reimilia", "url": "09.03.2021 - 4.1.png" },
        "2": { "author": "arcticsocks", "url": "09.03.2021 - 4.2.png" },
        "3": { "author": "xenon", "url": "09.03.2021 - 4.3.png" },
        "4": { "author": "hullperse", "url": "09.03.2021 - 4.4.png" },
        "5": { "author": "andbes", "url": "09.03.2021 - 4.5.png" }
      }
    },
    "book_62": {
      "author": "hullperse",
      "date": "09.03.2021",
      "images": {
        "1": { "author": "hullperse", "url": "09.03.2021 - 5.1.png" },
        "2": { "author": "andbes", "url": "09.03.2021 - 5.2.png" },
        "3": { "author": "arcticsocks", "url": "09.03.2021 - 5.3.png" },
        "4": { "author": "xenon", "url": "09.03.2021 - 5.4.png" },
        "5": { "author": "reimilia", "url": "09.03.2021 - 5.5.png" }
      }
    },
    "book_63": {
      "author": "hullperse",
      "date": "15.03.2021",
      "images": {
        "1": { "author": "hullperse", "url": "15.03.2021 - 1.1.png" },
        "2": { "author": "dualalarm", "url": "15.03.2021 - 1.2.png" },
        "3": { "author": "arcticsocks", "url": "15.03.2021 - 1.3.png" },
        "4": { "author": "andbes", "url": "15.03.2021 - 1.4.png" },
        "5": { "author": "reimilia", "url": "15.03.2021 - 1.5.png" }
      }
    },
    "book_64": {
      "author": "andbes",
      "date": "15.03.2021",
      "images": {
        "1": { "author": "andbes", "url": "15.03.2021 - 2.1.png" },
        "2": { "author": "arcticsocks", "url": "15.03.2021 - 2.2.png" },
        "3": { "author": "reimilia", "url": "15.03.2021 - 2.3.png" },
        "4": { "author": "hullperse", "url": "15.03.2021 - 2.4.png" },
        "5": { "author": "dualalarm", "url": "15.03.2021 - 2.5.png" }
      }
    },
    "book_65": {
      "author": "reimilia",
      "date": "15.03.2021",
      "images": {
        "1": { "author": "reimilia", "url": "15.03.2021 - 3.1.png" },
        "2": { "author": "hullperse", "url": "15.03.2021 - 3.2.png" },
        "3": { "author": "arcticsocks", "url": "15.03.2021 - 3.3.png" },
        "4": { "author": "dualalarm", "url": "15.03.2021 - 3.4.png" },
        "5": { "author": "andbes", "url": "15.03.2021 - 3.5.png" }
      }
    },
    "book_66": {
      "author": "dualalarm",
      "date": "15.03.2021",
      "images": {
        "1": { "author": "dualalarm", "url": "15.03.2021 - 4.1.png" },
        "2": { "author": "reimilia", "url": "15.03.2021 - 4.2.png" },
        "3": { "author": "hullperse", "url": "15.03.2021 - 4.3.png" },
        "4": { "author": "arcticsocks", "url": "15.03.2021 - 4.4.png" },
        "5": { "author": "andbes", "url": "15.03.2021 - 4.5.png" }
      }
    },
    "book_67": {
      "author": "arcticsocks",
      "date": "15.03.2021",
      "images": {
        "1": { "author": "arcticsocks", "url": "15.03.2021 - 5.1.png" },
        "2": { "author": "andbes", "url": "15.03.2021 - 5.2.png" },
        "3": { "author": "dualalarm", "url": "15.03.2021 - 5.3.png" },
        "4": { "author": "hullperse", "url": "15.03.2021 - 5.4.png" },
        "5": { "author": "reimilia", "url": "15.03.2021 - 5.5.png" }
      }
    },
    "book_68": {
      "author": "hullperse",
      "date": "19.06.2021",
      "images": {
        "1": { "author": "hullperse", "url": "19.06.2021 - 1.1.png" },
        "2": { "author": "roomins", "url": "19.06.2021 - 1.2.png" },
        "3": { "author": "reimilia", "url": "19.06.2021 - 1.3.png" },
        "4": { "author": "arcticsocks", "url": "19.06.2021 - 1.4.png" },
        "5": { "author": "andbes", "url": "19.06.2021 - 1.5.png" }
      }
    },
    "book_69": {
      "author": "roomins",
      "date": "19.06.2021",
      "images": {
        "1": { "author": "roomins", "url": "19.06.2021 - 2.1.png" },
        "2": { "author": "hullperse", "url": "19.06.2021 - 2.2.png" },
        "3": { "author": "andbes", "url": "19.06.2021 - 2.3.png" },
        "4": { "author": "arcticsocks", "url": "19.06.2021 - 2.4.png" },
        "5": { "author": "reimilia", "url": "19.06.2021 - 2.5.png" }
      }
    },
    "book_70": {
      "author": "andbes",
      "date": "19.06.2021",
      "images": {
        "1": { "author": "andbes", "url": "19.06.2021 - 3.1.png" },
        "2": { "author": "hullperse", "url": "19.06.2021 - 3.2.png" },
        "3": { "author": "roomins", "url": "19.06.2021 - 3.3.png" },
        "4": { "author": "arcticsocks", "url": "19.06.2021 - 3.4.png" },
        "5": { "author": "reimilia", "url": "19.06.2021 - 3.5.png" }
      }
    },
    "book_71": {
      "author": "reimilia",
      "date": "19.06.2021",
      "images": {
        "1": { "author": "reimilia", "url": "19.06.2021 - 4.1.png" },
        "2": { "author": "arcticsocks", "url": "19.06.2021 - 4.2.png" },
        "3": { "author": "roomins", "url": "19.06.2021 - 4.3.png" },
        "4": { "author": "andbes", "url": "19.06.2021 - 4.4.png" },
        "5": { "author": "hullperse", "url": "19.06.2021 - 4.5.png" }
      }
    },
    "book_72": {
      "author": "arcticsocks",
      "date": "19.06.2021",
      "images": {
        "1": { "author": "arcticsocks", "url": "19.06.2021 - 5.1.png" },
        "2": { "author": "andbes", "url": "19.06.2021 - 5.2.png" },
        "3": { "author": "reimilia", "url": "19.06.2021 - 5.3.png" },
        "4": { "author": "hullperse", "url": "19.06.2021 - 5.4.png" },
        "5": { "author": "roomins", "url": "19.06.2021 - 5.5.png" }
      }
    },
    "book_73": {
      "author": "reimilia",
      "date": "03.07.2021",
      "images": {
        "1": { "author": "reimilia", "url": "03.07.2021 - 1.1.png" },
        "2": { "author": "andbes", "url": "03.07.2021 - 1.2.png" },
        "3": { "author": "xenon", "url": "03.07.2021 - 1.3.png" },
        "4": { "author": "arcticsocks", "url": "03.07.2021 - 1.4.png" },
        "5": { "author": "hullperse", "url": "03.07.2021 - 1.5.png" }
      }
    },
    "book_74": {
      "author": "hullperse",
      "date": "03.07.2021",
      "images": {
        "1": { "author": "hullperse", "url": "03.07.2021 - 2.1.png" },
        "2": { "author": "arcticsocks", "url": "03.07.2021 - 2.2.png" },
        "3": { "author": "xenon", "url": "03.07.2021 - 2.3.png" },
        "4": { "author": "reimilia", "url": "03.07.2021 - 2.4.png" },
        "5": { "author": "andbes", "url": "03.07.2021 - 2.5.png" }
      }
    },
    "book_75": {
      "author": "andbes",
      "date": "03.07.2021",
      "images": {
        "1": { "author": "andbes", "url": "03.07.2021 - 3.1.png" },
        "2": { "author": "hullperse", "url": "03.07.2021 - 3.2.png" },
        "3": { "author": "arcticsocks", "url": "03.07.2021 - 3.3.png" },
        "4": { "author": "reimilia", "url": "03.07.2021 - 3.4.png" },
        "5": { "author": "xenon", "url": "03.07.2021 - 3.5.png" }
      }
    },
    "book_76": {
      "author": "arcticsocks",
      "date": "03.07.2021",
      "images": {
        "1": { "author": "arcticsocks", "url": "03.07.2021 - 4.1.png" },
        "2": { "author": "xenon", "url": "03.07.2021 - 4.2.png" },
        "3": { "author": "reimilia", "url": "03.07.2021 - 4.3.png" },
        "4": { "author": "hullperse", "url": "03.07.2021 - 4.4.png" },
        "5": { "author": "andbes", "url": "03.07.2021 - 4.5.png" }
      }
    },
    "book_77": {
      "author": "xenon",
      "date": "03.07.2021",
      "images": {
        "1": { "author": "xenon", "url": "03.07.2021 - 5.1.png" },
        "2": { "author": "andbes", "url": "03.07.2021 - 5.2.png" },
        "3": { "author": "hullperse", "url": "03.07.2021 - 5.3.png" },
        "4": { "author": "arcticsocks", "url": "03.07.2021 - 5.4.png" },
        "5": { "author": "reimilia", "url": "03.07.2021 - 5.5.png" }
      }
    },
    "book_78": {
      "author": "andbes",
      "date": "15.07.2021",
      "images": {
        "1": { "author": "andbes", "url": "15.07.2021 - 1.1.png" },
        "2": { "author": "roomins", "url": "15.07.2021 - 1.2.png" },
        "3": { "author": "hullperse", "url": "15.07.2021 - 1.3.png" },
        "4": { "author": "arcticsocks", "url": "15.07.2021 - 1.4.png" }
      }
    },
    "book_79": {
      "author": "arcticsocks",
      "date": "15.07.2021",
      "images": {
        "1": { "author": "arcticsocks", "url": "15.07.2021 - 2.1.png" },
        "2": { "author": "andbes", "url": "15.07.2021 - 2.2.png" },
        "3": { "author": "roomins", "url": "15.07.2021 - 2.3.png" },
        "4": { "author": "hullperse", "url": "15.07.2021 - 2.4.png" }
      }
    },
    "book_80": {
      "author": "hullperse",
      "date": "15.07.2021",
      "images": {
        "1": { "author": "hullperse", "url": "15.07.2021 - 3.1.png" },
        "2": { "author": "roomins", "url": "15.07.2021 - 3.2.png" },
        "3": { "author": "andbes", "url": "15.07.2021 - 3.3.png" },
        "4": { "author": "arcticsocks", "url": "15.07.2021 - 3.4.png" }
      }
    },
    "book_81": {
      "author": "roomins",
      "date": "15.07.2021",
      "images": {
        "1": { "author": "roomins", "url": "15.07.2021 - 4.1.png" },
        "2": { "author": "arcticsocks", "url": "15.07.2021 - 4.2.png" },
        "3": { "author": "hullperse", "url": "15.07.2021 - 4.3.png" },
        "4": { "author": "andbes", "url": "15.07.2021 - 4.4.png" }
      }
    },
    "book_82": {
      "author": "arcticsocks",
      "date": "24.07.2021",
      "images": {
        "1": { "author": "andbes", "url": "24.07.2021 - 1.1.png" },
        "2": { "author": "roomins", "url": "24.07.2021 - 1.2.png" },
        "3": { "author": "dualalarm", "url": "24.07.2021 - 1.3.png" },
        "4": { "author": "andbes", "url": "24.07.2021 - 1.4.png" },
        "5": { "author": "hullperse", "url": "24.07.2021 - 1.5.png" }
      }
    },
    "book_83": {
      "author": "andbes",
      "date": "24.07.2021",
      "images": {
        "1": { "author": "andbes", "url": "24.07.2021 - 2.1.png" },
        "2": { "author": "hullperse", "url": "24.07.2021 - 2.2.png" },
        "3": { "author": "arcticsocks", "url": "24.07.2021 - 2.3.png" },
        "4": { "author": "roomins", "url": "24.07.2021 - 2.4.png" },
        "5": { "author": "dualalarm", "url": "24.07.2021 - 2.5.png" }
      }
    },
    "book_84": {
      "author": "roomins",
      "date": "24.07.2021",
      "images": {
        "1": { "author": "roomins", "url": "24.07.2021 - 3.1.png" },
        "2": { "author": "arcticsocks", "url": "24.07.2021 - 3.2.png" },
        "3": { "author": "dualalarm", "url": "24.07.2021 - 3.3.png" },
        "4": { "author": "hullperse", "url": "24.07.2021 - 3.4.png" },
        "5": { "author": "andbes", "url": "24.07.2021 - 3.5.png" }
      }
    },
    "book_85": {
      "author": "dualalarm",
      "date": "24.07.2021",
      "images": {
        "1": { "author": "dualalarm", "url": "24.07.2021 - 4.1.png" },
        "2": { "author": "andbes", "url": "24.07.2021 - 4.2.png" },
        "3": { "author": "hullperse", "url": "24.07.2021 - 4.3.png" },
        "4": { "author": "arcticsocks", "url": "24.07.2021 - 4.4.png" },
        "5": { "author": "roomins", "url": "24.07.2021 - 4.5.png" }
      }
    },
    "book_86": {
      "author": "hullperse",
      "date": "24.07.2021",
      "images": {
        "1": { "author": "hullperse", "url": "24.07.2021 - 5.1.png" },
        "2": { "author": "andbes", "url": "24.07.2021 - 5.2.png" },
        "3": { "author": "roomins", "url": "24.07.2021 - 5.3.png" },
        "4": { "author": "arcticsocks", "url": "24.07.2021 - 5.4.png" },
        "5": { "author": "dualalarm", "url": "24.07.2021 - 5.5.png" }
      }
    },
    "book_87": {
      "author": "hullperse",
      "date": "02.08.2021",
      "images": {
        "1": { "author": "hullperse", "url": "02.08.2021 - 1.1.png" },
        "2": { "author": "roomins", "url": "02.08.2021 - 1.2.png" },
        "3": { "author": "etojebruh", "url": "02.08.2021 - 1.3.png" },
        "4": { "author": "andbes", "url": "02.08.2021 - 1.4.png" },
        "5": { "author": "arcticsocks", "url": "02.08.2021 - 1.5.png" }
      }
    },
    "book_88": {
      "author": "etojebruh",
      "date": "02.08.2021",
      "images": {
        "1": { "author": "etojebruh", "url": "02.08.2021 - 2.1.png" },
        "2": { "author": "arcticsocks", "url": "02.08.2021 - 2.2.png" },
        "3": { "author": "roomins", "url": "02.08.2021 - 2.3.png" },
        "4": { "author": "andbes", "url": "02.08.2021 - 2.4.png" },
        "5": { "author": "hullperse", "url": "02.08.2021 - 2.5.png" }
      }
    },
    "book_89": {
      "author": "andbes",
      "date": "02.08.2021",
      "images": {
        "1": { "author": "andbes", "url": "02.08.2021 - 3.1.png" },
        "2": { "author": "hullperse", "url": "02.08.2021 - 3.2.png" },
        "3": { "author": "roomins", "url": "02.08.2021 - 3.3.png" },
        "4": { "author": "etojebruh", "url": "02.08.2021 - 3.4.png" },
        "5": { "author": "arcticsocks", "url": "02.08.2021 - 3.5.png" }
      }
    },
    "book_90": {
      "author": "arcticsocks",
      "date": "02.08.2021",
      "images": {
        "1": { "author": "arcticsocks", "url": "02.08.2021 - 4.1.png" },
        "2": { "author": "etojebruh", "url": "02.08.2021 - 4.2.png" },
        "3": { "author": "hullperse", "url": "02.08.2021 - 4.3.png" },
        "4": { "author": "roomins", "url": "02.08.2021 - 4.4.png" },
        "5": { "author": "andbes", "url": "02.08.2021 - 4.5.png" }
      }
    },
    "book_91": {
      "author": "roomins",
      "date": "02.08.2021",
      "images": {
        "1": { "author": "roomins", "url": "02.08.2021 - 5.1.png" },
        "2": { "author": "andbes", "url": "02.08.2021 - 5.2.png" },
        "3": { "author": "arcticsocks", "url": "02.08.2021 - 5.3.png" },
        "4": { "author": "hullperse", "url": "02.08.2021 - 5.4.png" }
      }
    },
    "book_92": {
      "author": "dualalarm",
      "date": "14.11.2021",
      "images": {
        "1": { "author": "dualalarm", "url": "14.11.2021 - 1.1.png" },
        "2": { "author": "andbes", "url": "14.11.2021 - 1.2.png" },
        "3": { "author": "xenon", "url": "14.11.2021 - 1.3.png" },
        "4": { "author": "hullperse", "url": "14.11.2021 - 1.4.png" },
        "5": { "author": "arcticsocks", "url": "14.11.2021 - 1.5.png" }
      }
    },
    "book_93": {
      "author": "andbes",
      "date": "14.11.2021",
      "images": {
        "1": { "author": "andbes", "url": "14.11.2021 - 2.1.png" },
        "2": { "author": "hullperse", "url": "14.11.2021 - 2.2.png" },
        "3": { "author": "dualalarm", "url": "14.11.2021 - 2.3.png" },
        "4": { "author": "arcticsocks", "url": "14.11.2021 - 2.4.png" },
        "5": { "author": "xenon", "url": "14.11.2021 - 2.5.png" }
      }
    },
    "book_94": {
      "author": "xenon",
      "date": "14.11.2021",
      "images": {
        "1": { "author": "xenon", "url": "14.11.2021 - 3.1.png" },
        "2": { "author": "arcticsocks", "url": "14.11.2021 - 3.2.png" },
        "3": { "author": "hullperse", "url": "14.11.2021 - 3.3.png" },
        "4": { "author": "dualalarm", "url": "14.11.2021 - 3.4.png" },
        "5": { "author": "andbes", "url": "14.11.2021 - 3.5.png" }
      }
    },
    "book_95": {
      "author": "arcticsocks",
      "date": "14.11.2021",
      "images": {
        "1": { "author": "arcticsocks", "url": "14.11.2021 - 4.1.png" },
        "2": { "author": "andbes", "url": "14.11.2021 - 4.2.png" },
        "3": { "author": "xenon", "url": "14.11.2021 - 4.3.png" },
        "4": { "author": "dualalarm", "url": "14.11.2021 - 4.4.png" },
        "5": { "author": "andbes", "url": "14.11.2021 - 4.5.png" }
      }
    },
    "book_96": {
      "author": "hullperse",
      "date": "14.11.2021",
      "images": {
        "1": { "author": "hullperse", "url": "14.11.2021 - 5.1.png" },
        "2": { "author": "dualalarm", "url": "14.11.2021 - 5.2.png" },
        "3": { "author": "arcticsocks", "url": "14.11.2021 - 5.3.png" },
        "4": { "author": "xenon", "url": "14.11.2021 - 5.4.png" },
        "5": { "author": "andbes", "url": "14.11.2021 - 5.5.png" }
      }
    },
    "book_97": {
      "author": "hullperse",
      "date": "05.12.2021",
      "images": {
        "1": { "author": "hullperse", "url": "05.12.2021 - 1.1.png" },
        "2": { "author": "arcticsocks", "url": "05.12.2021 - 1.2.png" },
        "3": { "author": "xenon", "url": "05.12.2021 - 1.3.png" },
        "4": { "author": "roomins", "url": "05.12.2021 - 1.4.png" }
      }
    },
    "book_98": {
      "author": "arcticsocks",
      "date": "05.12.2021",
      "images": {
        "1": { "author": "arcticsocks", "url": "05.12.2021 - 2.1.png" },
        "2": { "author": "xenon", "url": "05.12.2021 - 2.2.png" },
        "3": { "author": "hullperse", "url": "05.12.2021 - 2.3.png" },
        "4": { "author": "roomins", "url": "05.12.2021 - 2.4.png" }
      }
    },
    "book_99": {
      "author": "reimilia",
      "date": "05.12.2021",
      "images": {
        "1": { "author": "reimilia", "url": "05.12.2021 - 3.1.png" },
        "2": { "author": "arcticsocks", "url": "05.12.2021 - 3.2.png" },
        "3": { "author": "xenon", "url": "05.12.2021 - 3.3.png" },
        "4": { "author": "hullperse", "url": "05.12.2021 - 3.4.png" }
      }
    },
    "book_100": {
      "author": "xenon",
      "date": "05.12.2021",
      "images": {
        "1": { "author": "xenon", "url": "05.12.2021 - 4.1.png" },
        "2": { "author": "roomins", "url": "05.12.2021 - 4.2.png" },
        "3": { "author": "hullperse", "url": "05.12.2021 - 4.3.png" },
        "4": { "author": "arcticsocks", "url": "05.12.2021 - 4.4.png" }
      }
    },
    "book_101": {
      "author": "andbes",
      "date": "02.01.2022",
      "images": {
        "1": { "author": "andbes", "url": "02.01.2022 - 1.1.png" },
        "2": { "author": "hullperse", "url": "02.01.2022 - 1.2.png" },
        "3": { "author": "xenon", "url": "02.01.2022 - 1.3.png" },
        "4": { "author": "arcticsocks", "url": "02.01.2022 - 1.4.png" },
        "5": { "author": "reimilia", "url": "02.01.2022 - 1.5.png" },
        "6": { "author": "xandrlevir", "url": "02.01.2022 - 1.6.png" }
      }
    },
    "book_102": {
      "author": "reimilia",
      "date": "02.01.2022",
      "images": {
        "1": { "author": "reimilia", "url": "02.01.2022 - 2.1.png" },
        "2": { "author": "andbes", "url": "02.01.2022 - 2.2.png" },
        "3": { "author": "hullperse", "url": "02.01.2022 - 2.3.png" },
        "4": { "author": "arcticsocks", "url": "02.01.2022 - 2.4.png" },
        "5": { "author": "xenon", "url": "02.01.2022 - 2.5.png" },
        "6": { "author": "xandrlevir", "url": "02.01.2022 - 2.6.png" }
      }
    },
    "book_103": {
      "author": "arcticsocks",
      "date": "02.01.2022",
      "images": {
        "1": { "author": "arcticsocks", "url": "02.01.2022 - 3.1.png" },
        "2": { "author": "hullperse", "url": "02.01.2022 - 3.2.png" },
        "3": { "author": "xenon", "url": "02.01.2022 - 3.3.png" },
        "4": { "author": "xandrlevir", "url": "02.01.2022 - 3.4.png" },
        "5": { "author": "reimilia", "url": "02.01.2022 - 3.5.png" },
        "6": { "author": "andbes", "url": "02.01.2022 - 3.6.png" }
      }
    },
    "book_104": {
      "author": "hullperse",
      "date": "02.01.2022",
      "images": {
        "1": { "author": "hullperse", "url": "02.01.2022 - 4.1.png" },
        "2": { "author": "reimilia", "url": "02.01.2022 - 4.2.png" },
        "3": { "author": "andbes", "url": "02.01.2022 - 4.3.png" },
        "4": { "author": "xandrlevir", "url": "02.01.2022 - 4.4.png" },
        "5": { "author": "xenon", "url": "02.01.2022 - 4.5.png" },
        "6": { "author": "arcticsocks", "url": "02.01.2022 - 4.6.png" }
      }
    },
    "book_105": {
      "author": "xandrlevir",
      "date": "02.01.2022",
      "images": {
        "1": { "author": "xandrlevir", "url": "02.01.2022 - 5.1.png" },
        "2": { "author": "arcticsocks", "url": "02.01.2022 - 5.2.png" },
        "3": { "author": "xenon", "url": "02.01.2022 - 5.3.png" },
        "4": { "author": "andbes", "url": "02.01.2022 - 5.4.png" },
        "5": { "author": "hullperse", "url": "02.01.2022 - 5.5.png" },
        "6": { "author": "reimilia", "url": "02.01.2022 - 5.6.png" }
      }
    },
    "book_106": {
      "author": "xenon",
      "date": "02.01.2022",
      "images": {
        "1": { "author": "xenon", "url": "02.01.2022 - 6.1.png" },
        "2": { "author": "andbes", "url": "02.01.2022 - 6.2.png" },
        "3": { "author": "xandrlevir", "url": "02.01.2022 - 6.3.png" },
        "4": { "author": "reimilia", "url": "02.01.2022 - 6.4.png" },
        "5": { "author": "hullperse", "url": "02.01.2022 - 6.5.png" },
        "6": { "author": "arcticsocks", "url": "02.01.2022 - 6.6.png" }
      }
    },
    "book_107": {
      "author": "andbes",
      "date": "19.03.2022",
      "images": {
        "1": { "author": "andbes", "url": "19.03.2022 - 1.1.png" },
        "2": { "author": "arcticsocks", "url": "19.03.2022 - 1.2.png" },
        "3": { "author": "xandrlevir", "url": "19.03.2022 - 1.3.png" },
        "4": { "author": "reimilia", "url": "19.03.2022 - 1.4.png" },
        "5": { "author": "hullperse", "url": "19.03.2022 - 1.5.png" }
      }
    },
    "book_108": {
      "author": "hullperse",
      "date": "19.03.2022",
      "images": {
        "1": { "author": "hullperse", "url": "19.03.2022 - 2.1.png" },
        "2": { "author": "andbes", "url": "19.03.2022 - 2.2.png" },
        "3": { "author": "xenon", "url": "19.03.2022 - 2.3.png" },
        "4": { "author": "reimilia", "url": "19.03.2022 - 2.4.png" },
        "5": { "author": "arcticsocks", "url": "19.03.2022 - 2.5.png" },
        "6": { "author": "xandrlevir", "url": "19.03.2022 - 2.6.png" }
      }
    },
    "book_109": {
      "author": "reimilia",
      "date": "19.03.2022",
      "images": {
        "1": { "author": "reimilia", "url": "19.03.2022 - 3.1.png" },
        "2": { "author": "hullperse", "url": "19.03.2022 - 3.2.png" },
        "3": { "author": "arcticsocks", "url": "19.03.2022 - 3.3.png" },
        "4": { "author": "xenon", "url": "19.03.2022 - 3.4.png" },
        "5": { "author": "andbes", "url": "19.03.2022 - 3.5.png" },
        "6": { "author": "xandrlevir", "url": "19.03.2022 - 3.6.png" }
      }
    },
    "book_110": {
      "author": "xandrlevir",
      "date": "19.03.2022",
      "images": {
        "1": { "author": "xandrlevir", "url": "19.03.2022 - 4.1.png" },
        "2": { "author": "xenon", "url": "19.03.2022 - 4.2.png" },
        "3": { "author": "reimilia", "url": "19.03.2022 - 4.3.png" },
        "4": { "author": "arcticsocks", "url": "19.03.2022 - 4.4.png" },
        "5": { "author": "andbes", "url": "19.03.2022 - 4.5.png" },
        "6": { "author": "hullperse", "url": "19.03.2022 - 4.6.png" }
      }
    },
    "book_111": {
      "author": "xenon",
      "date": "19.03.2022",
      "images": {
        "1": { "author": "xenon", "url": "19.03.2022 - 5.1.png" },
        "2": { "author": "hullperse", "url": "19.03.2022 - 5.2.png" },
        "3": { "author": "andbes", "url": "19.03.2022 - 5.3.png" },
        "4": { "author": "xandrlevir", "url": "19.03.2022 - 5.4.png" },
        "5": { "author": "reimilia", "url": "19.03.2022 - 5.5.png" },
        "6": { "author": "arcticsocks", "url": "19.03.2022 - 5.6.png" }
      }
    },
    "book_112": {
      "author": "arcticsocks",
      "date": "19.03.2022",
      "images": {
        "1": { "author": "arcticsocks", "url": "19.03.2022 - 6.1.png" },
        "2": { "author": "xandrlevir", "url": "19.03.2022 - 6.2.png" },
        "3": { "author": "reimilia", "url": "19.03.2022 - 6.3.png" },
        "4": { "author": "xenon", "url": "19.03.2022 - 6.4.png" },
        "5": { "author": "hullperse", "url": "19.03.2022 - 6.5.png" },
        "6": { "author": "andbes", "url": "19.03.2022 - 6.6.png" }
      }
    },
    "book_113": {
      "author": "arcticsocks",
      "date": "16.07.2022",
      "images": {
        "1": { "author": "arcticsocks", "url": "16.07.2022 - 1.1.png" },
        "2": { "author": "barcat", "url": "16.07.2022 - 1.2.png" },
        "3": { "author": "andbes", "url": "16.07.2022 - 1.3.png" },
        "4": { "author": "hullperse", "url": "16.07.2022 - 1.4.png" },
        "5": { "author": "xenon", "url": "16.07.2022 - 1.5.png" }
      }
    },
    "book_114": {
      "author": "hullperse",
      "date": "16.07.2022",
      "images": {
        "1": { "author": "hullperse", "url": "16.07.2022 - 2.1.png" },
        "2": { "author": "xenon", "url": "16.07.2022 - 2.2.png" },
        "3": { "author": "barcat", "url": "16.07.2022 - 2.3.png" },
        "4": { "author": "arcticsocks", "url": "16.07.2022 - 2.4.png" },
        "5": { "author": "andbes", "url": "16.07.2022 - 2.5.png" }
      }
    },
    "book_115": {
      "author": "barcat",
      "date": "16.07.2022",
      "images": {
        "1": { "author": "barcat", "url": "16.07.2022 - 3.1.png" },
        "2": { "author": "andbes", "url": "16.07.2022 - 3.2.png" },
        "3": { "author": "hullperse", "url": "16.07.2022 - 3.3.png" },
        "4": { "author": "arcticsocks", "url": "16.07.2022 - 3.4.png" },
        "5": { "author": "xenon", "url": "16.07.2022 - 3.5.png" }
      }
    },
    "book_116": {
      "author": "xenon",
      "date": "16.07.2022",
      "images": {
        "1": { "author": "xenon", "url": "16.07.2022 - 4.1.png" },
        "2": { "author": "hullperse", "url": "16.07.2022 - 4.2.png" },
        "3": { "author": "arcticsocks", "url": "16.07.2022 - 4.3.png" },
        "4": { "author": "andbes", "url": "16.07.2022 - 4.4.png" },
        "5": { "author": "barcat", "url": "16.07.2022 - 4.5.png" }
      }
    },
    "book_117": {
      "author": "andbes",
      "date": "16.07.2022",
      "images": {
        "1": { "author": "andbes", "url": "16.07.2022 - 5.1.png" },
        "2": { "author": "arcticsocks", "url": "16.07.2022 - 5.2.png" },
        "3": { "author": "barcat", "url": "16.07.2022 - 5.3.png" },
        "4": { "author": "hullperse", "url": "16.07.2022 - 5.4.png" },
        "5": { "author": "xenon", "url": "16.07.2022 - 5.5.png" }
      }
    },
    "book_118": {
      "author": "barcat",
      "date": "28.08.2022",
      "images": {
        "1": { "author": "barcat", "url": "28.08.2022 - 1.1.png" },
        "2": { "author": "hullperse", "url": "28.08.2022 - 1.2.png" },
        "3": { "author": "xenon", "url": "28.08.2022 - 1.3.png" },
        "4": { "author": "andbes", "url": "28.08.2022 - 1.4.png" },
        "5": { "author": "arcticsocks", "url": "28.08.2022 - 1.5.png" }
      }
    },
    "book_119": {
      "author": "andbes",
      "date": "28.08.2022",
      "images": {
        "1": { "author": "andbes", "url": "28.08.2022 - 2.1.png" },
        "2": { "author": "barcat", "url": "28.08.2022 - 2.2.png" },
        "3": { "author": "xenon", "url": "28.08.2022 - 2.3.png" },
        "4": { "author": "hullperse", "url": "28.08.2022 - 2.4.png" },
        "5": { "author": "arcticsocks", "url": "28.08.2022 - 2.5.png" }
      }
    },
    "book_120": {
      "author": "arcticsocks",
      "date": "28.08.2022",
      "images": {
        "1": { "author": "arcticsocks", "url": "28.08.2022 - 3.1.png" },
        "2": { "author": "andbes", "url": "28.08.2022 - 3.2.png" },
        "3": { "author": "barcat", "url": "28.08.2022 - 3.3.png" },
        "4": { "author": "xenon", "url": "28.08.2022 - 3.4.png" },
        "5": { "author": "hullperse", "url": "28.08.2022 - 3.5.png" }
      }
    },
    "book_121": {
      "author": "hullperse",
      "date": "28.08.2022",
      "images": {
        "1": { "author": "hullperse", "url": "28.08.2022 - 4.1.png" },
        "2": { "author": "arcticsocks", "url": "28.08.2022 - 4.2.png" },
        "3": { "author": "andbes", "url": "28.08.2022 - 4.3.png" },
        "4": { "author": "xenon", "url": "28.08.2022 - 4.4.png" },
        "5": { "author": "barcat", "url": "28.08.2022 - 4.5.png" }
      }
    },
    "book_122": {
      "author": "xenon",
      "date": "28.08.2022",
      "images": {
        "1": { "author": "xenon", "url": "28.08.2022 - 5.1.png" },
        "2": { "author": "hullperse", "url": "28.08.2022 - 5.2.png" },
        "3": { "author": "arcticsocks", "url": "28.08.2022 - 5.3.png" },
        "4": { "author": "barcat", "url": "28.08.2022 - 5.4.png" },
        "5": { "author": "andbes", "url": "28.08.2022 - 5.5.png" }
      }
    }
  }
]
